model_admin_autocomplete/__init__.py
model_admin_autocomplete/mixins.py
model_admin_autocomplete/views.py
django_model_admin_autocomplete-0.2.0.dist-info/LICENSE
django_model_admin_autocomplete-0.2.0.dist-info/METADATA
django_model_admin_autocomplete-0.2.0.dist-info/WHEEL
django_model_admin_autocomplete-0.2.0.dist-info/top_level.txt
django_model_admin_autocomplete-0.2.0.dist-info/RECORD
