Metadata-Version: 2.1
Name: django-model-admin-autocomplete
Version: 0.2.0
Summary: Tweaks for existing built-in Django"s autocomplete feature
Home-page: https://github.com/jerinpetergeorge/django-model-admin-autocomplete
Author: Jerin Peter George
Author-email: jerinpetergeorge@gmail.com
License: MIT-Zero
Download-URL: https://github.com/jerinpetergeorge/django-model-admin-autocomplete/tarball/0.2.0
Platform: UNKNOWN
